youandai/__init__.py
youandai/game.py
youandai-0.1.0.dist-info/licenses/LICENSE
youandai-0.1.0.dist-info/METADATA
youandai-0.1.0.dist-info/WHEEL
youandai-0.1.0.dist-info/entry_points.txt
youandai-0.1.0.dist-info/top_level.txt
youandai-0.1.0.dist-info/RECORD
