Metadata-Version: 2.4
Name: YouAndAi
Version: 0.1.0
Summary: A minimalist AI-powered text adventure game.
Home-page: https://github.com/Youssef0356/youandai
Author: Youssef0356
Classifier: Programming Language :: Python :: 3
Classifier: License :: OSI Approved :: MIT License
License-File: LICENSE
Requires-Dist: google-generativeai
Dynamic: author
Dynamic: classifier
Dynamic: description
Dynamic: description-content-type
Dynamic: home-page
Dynamic: license-file
Dynamic: requires-dist
Dynamic: summary
